assets/logo.png
examples/basic.py
examples/defaults.py
examples/list_and_tuples.py
examples/unions_and_optionals.py
tests/tests.py
typed_configparser/__init__.py
typed_configparser/exceptions.py
typed_configparser/parser.py
typed_configparser-1.1.0.dist-info/LICENSE
typed_configparser-1.1.0.dist-info/METADATA
typed_configparser-1.1.0.dist-info/WHEEL
typed_configparser-1.1.0.dist-info/top_level.txt
typed_configparser-1.1.0.dist-info/RECORD
