Metadata-Version: 2.1
Name: typed_configparser
Version: 1.1.0
Summary: A typed configparser
Author-email: Ankit Jain <ajatkj.dev@gmail.com>
License: MIT
Project-URL: Repository, https://github.com/ajatkj/typed_configparser
Keywords: configparser,typed
Classifier: License :: OSI Approved :: MIT License
Classifier: Programming Language :: Python :: 3 :: Only
Classifier: Programming Language :: Python :: 3.8
Classifier: Programming Language :: Python :: 3.9
Classifier: Programming Language :: Python :: 3.10
Classifier: Programming Language :: Python :: 3.11
Classifier: Programming Language :: Python :: 3.12
Classifier: Typing :: Typed
Requires-Python: >=3.8
License-File: LICENSE
